emmi_escpi/__init__.py
emmi_escpi/_version.py
emmi_escpi/application.py
emmi_escpi/main.py
emmi_escpi-0.6.0.dist-info/LICENSE
emmi_escpi-0.6.0.dist-info/METADATA
emmi_escpi-0.6.0.dist-info/WHEEL
emmi_escpi-0.6.0.dist-info/entry_points.txt
emmi_escpi-0.6.0.dist-info/top_level.txt
emmi_escpi-0.6.0.dist-info/RECORD
