Metadata-Version: 2.1
Name: emmi-escpi
Version: 0.6.0
Summary: EPICS-SCPI Integration Tool
Author-email: Florin Boariu <florin.pt@rootshell.ro>, Matthias Rössle <matthias.roessle@helmholtz-berlin.de>
Project-URL: Homepage, https://emmi.rootshell.ro/escpi
Project-URL: Source Code, https://gitlab.com/codedump2/escpi/
Project-URL: Bug Tracker, https://gitlab.com/codedump2/escpi/-/issues
Classifier: Programming Language :: Python :: 3
Classifier: License :: OSI Approved :: GNU General Public License v3 or later (GPLv3+)
Classifier: Operating System :: POSIX :: Linux
Classifier: Development Status :: 2 - Pre-Alpha
Classifier: Environment :: Console
Classifier: Intended Audience :: Science/Research
Classifier: Topic :: Scientific/Engineering
Requires-Python: >=3.8
License-File: LICENSE
Requires-Dist: emmi[scpi,softioc] >=0.6.0
Requires-Dist: pyvisa-py
Requires-Dist: pyvisa-sim
Provides-Extra: test
Requires-Dist: pytest ; extra == 'test'
Requires-Dist: pytest-cov ; extra == 'test'
Requires-Dist: pytest-asyncio ; extra == 'test'
